[{"name":"AGNYS RAQUEL SOUSA ABREU","job":" - UNIVERSIDADE FEDERAL DO PIAUI","link":"http://www.portaltransparencia.gov.br/servidores/OrgaoExercicio-DetalhaServidor.asp?IdServidor=2256602&CodOrgao=26279"},{"name":"ALANA MARA ALMEIDA MACEDO","job":" - UNIVERSIDADE FEDERAL DO PIAUI","link":"http://www.portaltransparencia.gov.br/servidores/OrgaoExercicio-DetalhaServidor.asp?IdServidor=2258988&CodOrgao=26279"},{"name":"ALCIR MARTINS PEREIRA","job":" - UNIVERSIDADE FEDERAL DO PIAUI","link":"http://www.portaltransparencia.gov.br/servidores/OrgaoExercicio-DetalhaServidor.asp?IdServidor=2248774&CodOrgao=26279"},{"name":"ALESSANDRA CARVALHO DE OLIVEIRA","job":" - UNIVERSIDADE FEDERAL DO PIAUI","link":"http://www.portaltransparencia.gov.br/servidores/OrgaoExercicio-DetalhaServidor.asp?IdServidor=2086402&CodOrgao=26279"},{"name":"ALEXANDRA DE SIQUEIRA CAJADO LIARTE","job":" - UNIVERSIDADE FEDERAL DO PIAUI","link":"http://www.portaltransparencia.gov.br/servidores/OrgaoExercicio-DetalhaServidor.asp?IdServidor=2092333&CodOrgao=26279"},{"name":"ALINE JEANE COSTA SOUSA","job":" - UNIVERSIDADE FEDERAL DO PIAUI","link":"http://www.portaltransparencia.gov.br/servidores/OrgaoExercicio-DetalhaServidor.asp?IdServidor=2078918&CodOrgao=26279"},{"name":"ALINE MACEDO DA SILVA","job":" - UNIVERSIDADE FEDERAL DO PIAUI","link":"http://www.portaltransparencia.gov.br/servidores/OrgaoExercicio-DetalhaServidor.asp?IdServidor=2261835&CodOrgao=26279"},{"name":"ALINE MARTINS DE SOUSA","job":" - UNIVERSIDADE FEDERAL DO PIAUI","link":"http://www.portaltransparencia.gov.br/servidores/OrgaoExercicio-DetalhaServidor.asp?IdServidor=2088161&CodOrgao=26279"},{"name":"AMANDA NOGUEIRA DE CASTRO E SILVA","job":"HOSPITAL UNIVERSITARIO DA UFPI - UNIVERSIDADE FEDERAL DO PIAUI","link":"http://www.portaltransparencia.gov.br/servidores/OrgaoExercicio-DetalhaServidor.asp?IdServidor=1120754&CodOrgao=26279"},{"name":"ANA KAROLINE MEDEIROS DOS REIS","job":" - UNIVERSIDADE FEDERAL DO PIAUI","link":"http://www.portaltransparencia.gov.br/servidores/OrgaoExercicio-DetalhaServidor.asp?IdServidor=2258526&CodOrgao=26279"},{"name":"ANA LETICIA PEREIRA ANDRADE","job":" - UNIVERSIDADE FEDERAL DO PIAUI","link":"http://www.portaltransparencia.gov.br/servidores/OrgaoExercicio-DetalhaServidor.asp?IdServidor=2257245&CodOrgao=26279"},{"name":"ANA LORENA DE CARVALHO LIMA","job":" - UNIVERSIDADE FEDERAL DO PIAUI","link":"http://www.portaltransparencia.gov.br/servidores/OrgaoExercicio-DetalhaServidor.asp?IdServidor=2089472&CodOrgao=26279"},{"name":"ANA MARIA DE SOUSA","job":" - UNIVERSIDADE FEDERAL DO PIAUI","link":"http://www.portaltransparencia.gov.br/servidores/OrgaoExercicio-DetalhaServidor.asp?IdServidor=2088887&CodOrgao=26279"},{"name":"ANA MAYARA BARROS OLIVEIRA","job":" - UNIVERSIDADE FEDERAL DO PIAUI","link":"http://www.portaltransparencia.gov.br/servidores/OrgaoExercicio-DetalhaServidor.asp?IdServidor=2079710&CodOrgao=26279"},{"name":"ANA PAULA DA SILVA SOARES","job":" - UNIVERSIDADE FEDERAL DO PIAUI","link":"http://www.portaltransparencia.gov.br/servidores/OrgaoExercicio-DetalhaServidor.asp?IdServidor=2258679&CodOrgao=26279"},{"name":"ANA RITA GONCALVES MELO","job":" - UNIVERSIDADE FEDERAL DO PIAUI","link":"http://www.portaltransparencia.gov.br/servidores/OrgaoExercicio-DetalhaServidor.asp?IdServidor=2249594&CodOrgao=26279"},{"name":"ANDRE FONSECA NUNES","job":" - UNIVERSIDADE FEDERAL DO PIAUI","link":"http://www.portaltransparencia.gov.br/servidores/OrgaoExercicio-DetalhaServidor.asp?IdServidor=1469620&CodOrgao=26279"},{"name":"ANDRE GONCALVES HONORIO CARVALHO","job":" - UNIVERSIDADE FEDERAL DO PIAUI","link":"http://www.portaltransparencia.gov.br/servidores/OrgaoExercicio-DetalhaServidor.asp?IdServidor=2090977&CodOrgao=26279"},{"name":"ANDREA DANNY VASCONCELOS CANCIO","job":" - UNIVERSIDADE FEDERAL DO PIAUI","link":"http://www.portaltransparencia.gov.br/servidores/OrgaoExercicio-DetalhaServidor.asp?IdServidor=2090176&CodOrgao=26279"},{"name":"ANDREA THAIS XAVIER RODRIGUEZ HURTADO","job":" - UNIVERSIDADE FEDERAL DO PIAUI","link":"http://www.portaltransparencia.gov.br/servidores/OrgaoExercicio-DetalhaServidor.asp?IdServidor=2126691&CodOrgao=26279"},{"name":"ANDRESSA DANIELA DE SOUSA","job":" - UNIVERSIDADE FEDERAL DO PIAUI","link":"http://www.portaltransparencia.gov.br/servidores/OrgaoExercicio-DetalhaServidor.asp?IdServidor=2249882&CodOrgao=26279"},{"name":"ANDRESSA KELLY BARBOSA RUFINO","job":" - UNIVERSIDADE FEDERAL DO PIAUI","link":"http://www.portaltransparencia.gov.br/servidores/OrgaoExercicio-DetalhaServidor.asp?IdServidor=2258766&CodOrgao=26279"},{"name":"ANETTE SANTIAGO PEREIRA","job":"PROFESSOR DO MAGISTERIO SUPERIOR","link":"http://www.portaltransparencia.gov.br/servidores/OrgaoExercicio-DetalhaServidor.asp?IdServidor=1401492&CodOrgao=26279"},{"name":"ANGELA PEREIRA LOPES DE OLIVEIRA","job":"ENFERMEIRO - 36H","link":"http://www.portaltransparencia.gov.br/servidores/OrgaoExercicio-DetalhaServidor.asp?IdServidor=1670783&CodOrgao=26279"},{"name":"ANTONIO CHESLEM DE SOUZA","job":" - UNIVERSIDADE FEDERAL DO PIAUI","link":"http://www.portaltransparencia.gov.br/servidores/OrgaoExercicio-DetalhaServidor.asp?IdServidor=2250725&CodOrgao=26279"},{"name":"ANTONIO DE JESUS DA SILVA LEANDRO","job":" - UNIVERSIDADE FEDERAL DO PIAUI","link":"http://www.portaltransparencia.gov.br/servidores/OrgaoExercicio-DetalhaServidor.asp?IdServidor=2148224&CodOrgao=26279"},{"name":"ATHANA DE OLIVEIRA CAVALCANTE","job":" - UNIVERSIDADE FEDERAL DO PIAUI","link":"http://www.portaltransparencia.gov.br/servidores/OrgaoExercicio-DetalhaServidor.asp?IdServidor=2084795&CodOrgao=26279"},{"name":"BARBARA DE MORAIS BORBA","job":" - UNIVERSIDADE FEDERAL DO PIAUI","link":"http://www.portaltransparencia.gov.br/servidores/OrgaoExercicio-DetalhaServidor.asp?IdServidor=2090616&CodOrgao=26279"},{"name":"BEATRIZ DE OLIVEIRA FREIRE","job":" - UNIVERSIDADE FEDERAL DO PIAUI","link":"http://www.portaltransparencia.gov.br/servidores/OrgaoExercicio-DetalhaServidor.asp?IdServidor=2250149&CodOrgao=26279"},{"name":"BENONI CARVALHO JUNIOR","job":" - UNIVERSIDADE FEDERAL DO PIAUI","link":"http://www.portaltransparencia.gov.br/servidores/OrgaoExercicio-DetalhaServidor.asp?IdServidor=2083421&CodOrgao=26279"},{"name":"BETHANIA LUCIANA DOS SANTOS HOLANDA","job":" - UNIVERSIDADE FEDERAL DO PIAUI","link":"http://www.portaltransparencia.gov.br/servidores/OrgaoExercicio-DetalhaServidor.asp?IdServidor=2251796&CodOrgao=26279"},{"name":"BIANCA GONCALVES BEZERRA DE LIMA","job":" - UNIVERSIDADE FEDERAL DO PIAUI","link":"http://www.portaltransparencia.gov.br/servidores/OrgaoExercicio-DetalhaServidor.asp?IdServidor=2133693&CodOrgao=26279"},{"name":"BRENNO DE SOUSA ANDRADE","job":" - UNIVERSIDADE FEDERAL DO PIAUI","link":"http://www.portaltransparencia.gov.br/servidores/OrgaoExercicio-DetalhaServidor.asp?IdServidor=2082166&CodOrgao=26279"},{"name":"BRUNA DE OLIVEIRA MARTINS","job":" - UNIVERSIDADE FEDERAL DO PIAUI","link":"http://www.portaltransparencia.gov.br/servidores/OrgaoExercicio-DetalhaServidor.asp?IdServidor=2257712&CodOrgao=26279"},{"name":"CAETANO CORTEZ RUFINO FILHO","job":"MEDICO-AREA","link":"http://www.portaltransparencia.gov.br/servidores/OrgaoExercicio-DetalhaServidor.asp?IdServidor=1647831&CodOrgao=26279"},{"name":"CARLA MIKAELLA DE MOURA BRASIL","job":" - UNIVERSIDADE FEDERAL DO PIAUI","link":"http://www.portaltransparencia.gov.br/servidores/OrgaoExercicio-DetalhaServidor.asp?IdServidor=2255493&CodOrgao=26279"},{"name":"CARLOS AUGUSTO OLIVEIRA SANTOS","job":" - UNIVERSIDADE FEDERAL DO PIAUI","link":"http://www.portaltransparencia.gov.br/servidores/OrgaoExercicio-DetalhaServidor.asp?IdServidor=2259362&CodOrgao=26279"},{"name":"CARLOS EDUARDO ALMEIDA SOUSA","job":" - UNIVERSIDADE FEDERAL DO PIAUI","link":"http://www.portaltransparencia.gov.br/servidores/OrgaoExercicio-DetalhaServidor.asp?IdServidor=2090140&CodOrgao=26279"},{"name":"CARLOS EUGENIO DE OLIVEIRA BATISTA MEIRELES","job":" - UNIVERSIDADE FEDERAL DO PIAUI","link":"http://www.portaltransparencia.gov.br/servidores/OrgaoExercicio-DetalhaServidor.asp?IdServidor=2259086&CodOrgao=26279"},{"name":"CAROLINE PINHEIRO LIMA","job":" - UNIVERSIDADE FEDERAL DO PIAUI","link":"http://www.portaltransparencia.gov.br/servidores/OrgaoExercicio-DetalhaServidor.asp?IdServidor=2255796&CodOrgao=26279"},{"name":"CATARINA PESSOA CARDOSO","job":" - UNIVERSIDADE FEDERAL DO PIAUI","link":"http://www.portaltransparencia.gov.br/servidores/OrgaoExercicio-DetalhaServidor.asp?IdServidor=2258243&CodOrgao=26279"},{"name":"CATARINA RAFAELA ALVES DA SILVA","job":" - UNIVERSIDADE FEDERAL DO PIAUI","link":"http://www.portaltransparencia.gov.br/servidores/OrgaoExercicio-DetalhaServidor.asp?IdServidor=2079535&CodOrgao=26279"},{"name":"CAUBI DE ARAUJO MEDEIROS","job":" - UNIVERSIDADE FEDERAL DO PIAUI","link":"http://www.portaltransparencia.gov.br/servidores/OrgaoExercicio-DetalhaServidor.asp?IdServidor=1759953&CodOrgao=26279"},{"name":"CIPRIANO BARBOSA DE SOUSA","job":"PROFESSOR 3 GRAU - SUBSTITUTO","link":"http://www.portaltransparencia.gov.br/servidores/OrgaoExercicio-DetalhaServidor.asp?IdServidor=1734443&CodOrgao=26279"},{"name":"CLAYRA RODRIGUES DE SOUSA","job":" - UNIVERSIDADE FEDERAL DO PIAUI","link":"http://www.portaltransparencia.gov.br/servidores/OrgaoExercicio-DetalhaServidor.asp?IdServidor=2253391&CodOrgao=26279"},{"name":"CLEIDIANE DA CONCEICAO ALVES","job":" - UNIVERSIDADE FEDERAL DO PIAUI","link":"http://www.portaltransparencia.gov.br/servidores/OrgaoExercicio-DetalhaServidor.asp?IdServidor=2261397&CodOrgao=26279"},{"name":"CRISTIANE COELHO COSTA","job":" - UNIVERSIDADE FEDERAL DO PIAUI","link":"http://www.portaltransparencia.gov.br/servidores/OrgaoExercicio-DetalhaServidor.asp?IdServidor=2250565&CodOrgao=26279"},{"name":"DANIEL CELESTINO DE SOUSA","job":" - UNIVERSIDADE FEDERAL DO PIAUI","link":"http://www.portaltransparencia.gov.br/servidores/OrgaoExercicio-DetalhaServidor.asp?IdServidor=2092258&CodOrgao=26279"},{"name":"DANIELE DE OLIVEIRA RODRIGUES","job":" - UNIVERSIDADE FEDERAL DO PIAUI","link":"http://www.portaltransparencia.gov.br/servidores/OrgaoExercicio-DetalhaServidor.asp?IdServidor=2251884&CodOrgao=26279"},{"name":"DANUSA DA PAZ OLIVEIRA DE SOUSA LEAL","job":" - UNIVERSIDADE FEDERAL DO PIAUI","link":"http://www.portaltransparencia.gov.br/servidores/OrgaoExercicio-DetalhaServidor.asp?IdServidor=2091525&CodOrgao=26279"},{"name":"DAYANA MARIA DO NASCIMENTO","job":" - UNIVERSIDADE FEDERAL DO PIAUI","link":"http://www.portaltransparencia.gov.br/servidores/OrgaoExercicio-DetalhaServidor.asp?IdServidor=2087598&CodOrgao=26279"},{"name":"DENISE EVELYN MACHADO DE ALMEIDA","job":" - UNIVERSIDADE FEDERAL DO PIAUI","link":"http://www.portaltransparencia.gov.br/servidores/OrgaoExercicio-DetalhaServidor.asp?IdServidor=2083557&CodOrgao=26279"},{"name":"DUANNE MENDES GOMES","job":" - UNIVERSIDADE FEDERAL DO PIAUI","link":"http://www.portaltransparencia.gov.br/servidores/OrgaoExercicio-DetalhaServidor.asp?IdServidor=2258867&CodOrgao=26279"},{"name":"EDILDETE SENE PACHECO","job":" - UNIVERSIDADE FEDERAL DO PIAUI","link":"http://www.portaltransparencia.gov.br/servidores/OrgaoExercicio-DetalhaServidor.asp?IdServidor=2260570&CodOrgao=26279"},{"name":"EDINARI NUNES DE SOUSA LOPES","job":" - UNIVERSIDADE FEDERAL DO PIAUI","link":"http://www.portaltransparencia.gov.br/servidores/OrgaoExercicio-DetalhaServidor.asp?IdServidor=2017331&CodOrgao=26279"},{"name":"EGLESIA RODRIGUES LEITE FERNANDES","job":" - UNIVERSIDADE FEDERAL DO PIAUI","link":"http://www.portaltransparencia.gov.br/servidores/OrgaoExercicio-DetalhaServidor.asp?IdServidor=2256556&CodOrgao=26279"},{"name":"ELDO JOSE RODRIGUES DOS SANTOS","job":" - UNIVERSIDADE FEDERAL DO PIAUI","link":"http://www.portaltransparencia.gov.br/servidores/OrgaoExercicio-DetalhaServidor.asp?IdServidor=2247505&CodOrgao=26279"},{"name":"ELIEIDE SOARES DE OLIVEIRA","job":" - UNIVERSIDADE FEDERAL DO PIAUI","link":"http://www.portaltransparencia.gov.br/servidores/OrgaoExercicio-DetalhaServidor.asp?IdServidor=2255828&CodOrgao=26279"},{"name":"ELIZAMA DOS SANTOS COSTA","job":" - UNIVERSIDADE FEDERAL DO PIAUI","link":"http://www.portaltransparencia.gov.br/servidores/OrgaoExercicio-DetalhaServidor.asp?IdServidor=2090476&CodOrgao=26279"},{"name":"ELMA RITA ALBUQUERQUE AMORIM","job":" - UNIVERSIDADE FEDERAL DO PIAUI","link":"http://www.portaltransparencia.gov.br/servidores/OrgaoExercicio-DetalhaServidor.asp?IdServidor=2104412&CodOrgao=26279"},{"name":"ESTEFANE KELLY DIAS ARAUJO","job":" - UNIVERSIDADE FEDERAL DO PIAUI","link":"http://www.portaltransparencia.gov.br/servidores/OrgaoExercicio-DetalhaServidor.asp?IdServidor=2256464&CodOrgao=26279"},{"name":"EWERTON DANIEL ROCHA RODRIGUES","job":" - UNIVERSIDADE FEDERAL DO PIAUI","link":"http://www.portaltransparencia.gov.br/servidores/OrgaoExercicio-DetalhaServidor.asp?IdServidor=1449772&CodOrgao=26279"},{"name":"FABRICIO MAGALHAES DE AZEVEDO","job":" - UNIVERSIDADE FEDERAL DO PIAUI","link":"http://www.portaltransparencia.gov.br/servidores/OrgaoExercicio-DetalhaServidor.asp?IdServidor=2084565&CodOrgao=26279"},{"name":"FELIPE OSORIO MARQUES","job":" - UNIVERSIDADE FEDERAL DO PIAUI","link":"http://www.portaltransparencia.gov.br/servidores/OrgaoExercicio-DetalhaServidor.asp?IdServidor=2082946&CodOrgao=26279"},{"name":"FERNANDA CRISTINA DE ALMEIDA RIBEIRO","job":" - UNIVERSIDADE FEDERAL DO PIAUI","link":"http://www.portaltransparencia.gov.br/servidores/OrgaoExercicio-DetalhaServidor.asp?IdServidor=2255571&CodOrgao=26279"},{"name":"FERNANDA DE MACEDO LOPES","job":" - UNIVERSIDADE FEDERAL DO PIAUI","link":"http://www.portaltransparencia.gov.br/servidores/OrgaoExercicio-DetalhaServidor.asp?IdServidor=2082353&CodOrgao=26279"},{"name":"FERNANDA PINTO DA SILVA","job":" - UNIVERSIDADE FEDERAL DO PIAUI","link":"http://www.portaltransparencia.gov.br/servidores/OrgaoExercicio-DetalhaServidor.asp?IdServidor=1318855&CodOrgao=26279"},{"name":"FERNANDO BARBOSA DE SOUSA","job":" - UNIVERSIDADE FEDERAL DO PIAUI","link":"http://www.portaltransparencia.gov.br/servidores/OrgaoExercicio-DetalhaServidor.asp?IdServidor=2257973&CodOrgao=26279"},{"name":"FERNANDO SERGIO PEREIRA DE SOUSA","job":"PROFESSOR DO MAGISTERIO SUPERIOR","link":"http://www.portaltransparencia.gov.br/servidores/OrgaoExercicio-DetalhaServidor.asp?IdServidor=1763126&CodOrgao=26279"},{"name":"FRANCISCA EDINEIA MORAIS DA SILVA","job":" - UNIVERSIDADE FEDERAL DO PIAUI","link":"http://www.portaltransparencia.gov.br/servidores/OrgaoExercicio-DetalhaServidor.asp?IdServidor=2263439&CodOrgao=26279"},{"name":"FRANCISCO CESAR DE OLIVEIRA GONCALVES","job":" - UNIVERSIDADE FEDERAL DO PIAUI","link":"http://www.portaltransparencia.gov.br/servidores/OrgaoExercicio-DetalhaServidor.asp?IdServidor=2259420&CodOrgao=26279"},{"name":"FRANCISCO DAS CHAGAS DE OLIVEIRA JUNIOR","job":" - UNIVERSIDADE FEDERAL DO PIAUI","link":"http://www.portaltransparencia.gov.br/servidores/OrgaoExercicio-DetalhaServidor.asp?IdServidor=2019059&CodOrgao=26279"},{"name":"FRANCISCO LISBOA DE SOUSA JUNIOR","job":" - UNIVERSIDADE FEDERAL DO PIAUI","link":"http://www.portaltransparencia.gov.br/servidores/OrgaoExercicio-DetalhaServidor.asp?IdServidor=2258760&CodOrgao=26279"},{"name":"FRANKELINE GONCALVES DE AREA LEAO","job":" - UNIVERSIDADE FEDERAL DO PIAUI","link":"http://www.portaltransparencia.gov.br/servidores/OrgaoExercicio-DetalhaServidor.asp?IdServidor=2090259&CodOrgao=26279"},{"name":"GABRIELLA MARREIROS DE CARVALHO LEITE","job":" - UNIVERSIDADE FEDERAL DO PIAUI","link":"http://www.portaltransparencia.gov.br/servidores/OrgaoExercicio-DetalhaServidor.asp?IdServidor=2251399&CodOrgao=26279"},{"name":"GEDEAO LUSTOSA RIBEIRO NETO","job":" - UNIVERSIDADE FEDERAL DO PIAUI","link":"http://www.portaltransparencia.gov.br/servidores/OrgaoExercicio-DetalhaServidor.asp?IdServidor=1808791&CodOrgao=26279"},{"name":"GEORGYA ALMEIDA BRITO","job":"PROFESSOR 3 GRAU - SUBSTITUTO","link":"http://www.portaltransparencia.gov.br/servidores/OrgaoExercicio-DetalhaServidor.asp?IdServidor=1502941&CodOrgao=26279"},{"name":"GERSON TAVARES PESSOA","job":" - UNIVERSIDADE FEDERAL DO PIAUI","link":"http://www.portaltransparencia.gov.br/servidores/OrgaoExercicio-DetalhaServidor.asp?IdServidor=2090526&CodOrgao=26279"},{"name":"GLADS IUBY ALMEIDA DE MELO","job":" - UNIVERSIDADE FEDERAL DO PIAUI","link":"http://www.portaltransparencia.gov.br/servidores/OrgaoExercicio-DetalhaServidor.asp?IdServidor=2090330&CodOrgao=26279"},{"name":"GUILHERME DE CARVALHO PAULO MARCOS","job":" - UNIVERSIDADE FEDERAL DO PIAUI","link":"http://www.portaltransparencia.gov.br/servidores/OrgaoExercicio-DetalhaServidor.asp?IdServidor=1592426&CodOrgao=26279"},{"name":"GUILHERME HENRIQUE MENDES LEAL DE SOUSA MARTINS","job":" - UNIVERSIDADE FEDERAL DO PIAUI","link":"http://www.portaltransparencia.gov.br/servidores/OrgaoExercicio-DetalhaServidor.asp?IdServidor=2091410&CodOrgao=26279"},{"name":"GUILHERME SOARES BORGES","job":"01/03/2017","link":"http://www.portaltransparencia.gov.br/servidores/OrgaoExercicio-DetalhaServidor.asp?IdServidor=2252406&CodOrgao=26279"},{"name":"HERTON LUIZ ALVES SALES FILHO","job":" - UNIVERSIDADE FEDERAL DO PIAUI","link":"http://www.portaltransparencia.gov.br/servidores/OrgaoExercicio-DetalhaServidor.asp?IdServidor=2251348&CodOrgao=26279"},{"name":"IAN DE OLIVEIRA SILVA","job":" - UNIVERSIDADE FEDERAL DO PIAUI","link":"http://www.portaltransparencia.gov.br/servidores/OrgaoExercicio-DetalhaServidor.asp?IdServidor=2084724&CodOrgao=26279"},{"name":"IARA JESSICA BARRETO SILVA","job":" - UNIVERSIDADE FEDERAL DO PIAUI","link":"http://www.portaltransparencia.gov.br/servidores/OrgaoExercicio-DetalhaServidor.asp?IdServidor=2251608&CodOrgao=26279"},{"name":"IARA PATRICIA MOURA ROCHA","job":" - UNIVERSIDADE FEDERAL DO PIAUI","link":"http://www.portaltransparencia.gov.br/servidores/OrgaoExercicio-DetalhaServidor.asp?IdServidor=2078733&CodOrgao=26279"},{"name":"IGOR ALMEIDA SILVA","job":" - UNIVERSIDADE FEDERAL DO PIAUI","link":"http://www.portaltransparencia.gov.br/servidores/OrgaoExercicio-DetalhaServidor.asp?IdServidor=2253387&CodOrgao=26279"},{"name":"ILUSKA CASTRO DOS SANTOS","job":" - UNIVERSIDADE FEDERAL DO PIAUI","link":"http://www.portaltransparencia.gov.br/servidores/OrgaoExercicio-DetalhaServidor.asp?IdServidor=2256679&CodOrgao=26279"},{"name":"IONE CRISTINA DE MENESES EVANGELISTA","job":" - UNIVERSIDADE FEDERAL DO PIAUI","link":"http://www.portaltransparencia.gov.br/servidores/OrgaoExercicio-DetalhaServidor.asp?IdServidor=2137981&CodOrgao=26279"},{"name":"IRAN BATISTA DE BRITO","job":" - UNIVERSIDADE FEDERAL DO PIAUI","link":"http://www.portaltransparencia.gov.br/servidores/OrgaoExercicio-DetalhaServidor.asp?IdServidor=2079871&CodOrgao=26279"},{"name":"ISAAC ANTAO DE CARVALHO NETO","job":" - UNIVERSIDADE FEDERAL DO PIAUI","link":"http://www.portaltransparencia.gov.br/servidores/OrgaoExercicio-DetalhaServidor.asp?IdServidor=2255170&CodOrgao=26279"},{"name":"ISABELA MARIA MAGALHAES SALES","job":" - UNIVERSIDADE FEDERAL DO PIAUI","link":"http://www.portaltransparencia.gov.br/servidores/OrgaoExercicio-DetalhaServidor.asp?IdServidor=2265166&CodOrgao=26279"},{"name":"ISADORA NOLETO BARBOSA","job":" - UNIVERSIDADE FEDERAL DO PIAUI","link":"http://www.portaltransparencia.gov.br/servidores/OrgaoExercicio-DetalhaServidor.asp?IdServidor=2255244&CodOrgao=26279"},{"name":"IULIANA MARJORY MARTINS RIBEIRO","job":" - UNIVERSIDADE FEDERAL DO PIAUI","link":"http://www.portaltransparencia.gov.br/servidores/OrgaoExercicio-DetalhaServidor.asp?IdServidor=2082184&CodOrgao=26279"},{"name":"IVANA MAYRA DA SILVA LIRA","job":" - UNIVERSIDADE FEDERAL DO PIAUI","link":"http://www.portaltransparencia.gov.br/servidores/OrgaoExercicio-DetalhaServidor.asp?IdServidor=2261660&CodOrgao=26279"},{"name":"JACIRA OLIVEIRA IBIAPINA","job":" - UNIVERSIDADE FEDERAL DO PIAUI","link":"http://www.portaltransparencia.gov.br/servidores/OrgaoExercicio-DetalhaServidor.asp?IdServidor=1142315&CodOrgao=26279"},{"name":"JACKSON DOS SANTOS ROCHA","job":" - UNIVERSIDADE FEDERAL DO PIAUI","link":"http://www.portaltransparencia.gov.br/servidores/OrgaoExercicio-DetalhaServidor.asp?IdServidor=1367331&CodOrgao=26279"},{"name":"JADER BARROZO DE CARVALHO","job":"ASSISTENTE EM ADMINISTRACAO","link":"http://www.portaltransparencia.gov.br/servidores/OrgaoExercicio-DetalhaServidor.asp?IdServidor=1178560&CodOrgao=26279"},{"name":"JADIEL MARINHO CARDOSO","job":" - UNIVERSIDADE FEDERAL DO PIAUI","link":"http://www.portaltransparencia.gov.br/servidores/OrgaoExercicio-DetalhaServidor.asp?IdServidor=2263237&CodOrgao=26279"},{"name":"JAMES FREDERICO ROCHA PACHECO","job":" - UNIVERSIDADE FEDERAL DO PIAUI","link":"http://www.portaltransparencia.gov.br/servidores/OrgaoExercicio-DetalhaServidor.asp?IdServidor=2253082&CodOrgao=26279"},{"name":"JANAINA DO NASCIMENTO ROCHA","job":"ASSISTENTE EM ADMINISTRACAO","link":"http://www.portaltransparencia.gov.br/servidores/OrgaoExercicio-DetalhaServidor.asp?IdServidor=1970261&CodOrgao=26279"},{"name":"JEFFERSON BRUNO SOARES OLIVEIRA","job":" - UNIVERSIDADE FEDERAL DO PIAUI","link":"http://www.portaltransparencia.gov.br/servidores/OrgaoExercicio-DetalhaServidor.asp?IdServidor=2253446&CodOrgao=26279"},{"name":"JEFFERSON HALLISSON LUSTOSA DA SILVA","job":" - UNIVERSIDADE FEDERAL DO PIAUI","link":"http://www.portaltransparencia.gov.br/servidores/OrgaoExercicio-DetalhaServidor.asp?IdServidor=2258820&CodOrgao=26279"},{"name":"JESSICA ANDRESSA SOARES DE CARVALHO","job":" - UNIVERSIDADE FEDERAL DO PIAUI","link":"http://www.portaltransparencia.gov.br/servidores/OrgaoExercicio-DetalhaServidor.asp?IdServidor=2102297&CodOrgao=26279"},{"name":"JESSICA DE MOURA CAMINHA","job":" - UNIVERSIDADE FEDERAL DO PIAUI","link":"http://www.portaltransparencia.gov.br/servidores/OrgaoExercicio-DetalhaServidor.asp?IdServidor=2261998&CodOrgao=26279"},{"name":"JESSICA DE SOUSA COSTA","job":" - UNIVERSIDADE FEDERAL DO PIAUI","link":"http://www.portaltransparencia.gov.br/servidores/OrgaoExercicio-DetalhaServidor.asp?IdServidor=2249118&CodOrgao=26279"},{"name":"JHOONATARRATY FONSECA DE SENA","job":" - UNIVERSIDADE FEDERAL DO PIAUI","link":"http://www.portaltransparencia.gov.br/servidores/OrgaoExercicio-DetalhaServidor.asp?IdServidor=1456377&CodOrgao=26279"},{"name":"JOAO LENON DE SOUSA","job":" - UNIVERSIDADE FEDERAL DO PIAUI","link":"http://www.portaltransparencia.gov.br/servidores/OrgaoExercicio-DetalhaServidor.asp?IdServidor=2150097&CodOrgao=26279"},{"name":"JOAO MARQUES MENDES NETO","job":" - UNIVERSIDADE FEDERAL DO PIAUI","link":"http://www.portaltransparencia.gov.br/servidores/OrgaoExercicio-DetalhaServidor.asp?IdServidor=2255088&CodOrgao=26279"},{"name":"JOAO MESSIAS FREITAS MELO","job":"ASSISTENTE EM ADMINISTRACAO","link":"http://www.portaltransparencia.gov.br/servidores/OrgaoExercicio-DetalhaServidor.asp?IdServidor=1862709&CodOrgao=26279"},{"name":"JOAO NORIVAL LIMA JUNIOR","job":" - UNIVERSIDADE FEDERAL DO PIAUI","link":"http://www.portaltransparencia.gov.br/servidores/OrgaoExercicio-DetalhaServidor.asp?IdServidor=2252273&CodOrgao=26279"},{"name":"JOAQUIM GUERRA DE OLIVEIRA NETO","job":" - UNIVERSIDADE FEDERAL DO PIAUI","link":"http://www.portaltransparencia.gov.br/servidores/OrgaoExercicio-DetalhaServidor.asp?IdServidor=2086023&CodOrgao=26279"},{"name":"JORDANO SAMPAIO GUIMARAES SILVA","job":" - UNIVERSIDADE FEDERAL DO PIAUI","link":"http://www.portaltransparencia.gov.br/servidores/OrgaoExercicio-DetalhaServidor.asp?IdServidor=2090465&CodOrgao=26279"},{"name":"JOSE BISPO DE SOUSA NETO","job":" - UNIVERSIDADE FEDERAL DO PIAUI","link":"http://www.portaltransparencia.gov.br/servidores/OrgaoExercicio-DetalhaServidor.asp?IdServidor=2087074&CodOrgao=26279"},{"name":"JOSE HUMBERTO SANTOS FILHO","job":" - UNIVERSIDADE FEDERAL DO PIAUI","link":"http://www.portaltransparencia.gov.br/servidores/OrgaoExercicio-DetalhaServidor.asp?IdServidor=2088518&CodOrgao=26279"},{"name":"JOSE PESSOA LEAL","job":"PROFESSOR DO MAGISTERIO SUPERIOR","link":"http://www.portaltransparencia.gov.br/servidores/OrgaoExercicio-DetalhaServidor.asp?IdServidor=1741696&CodOrgao=26279"},{"name":"JOSE RODRIGO BEZERRA SOUSA","job":" - UNIVERSIDADE FEDERAL DO PIAUI","link":"http://www.portaltransparencia.gov.br/servidores/OrgaoExercicio-DetalhaServidor.asp?IdServidor=2083618&CodOrgao=26279"},{"name":"JOSE SIMIAO DA CRUZ JUNIOR","job":" - UNIVERSIDADE FEDERAL DO PIAUI","link":"http://www.portaltransparencia.gov.br/servidores/OrgaoExercicio-DetalhaServidor.asp?IdServidor=2267868&CodOrgao=26279"},{"name":"JOSE TAFFAREL BATISTA LIMA","job":" - UNIVERSIDADE FEDERAL DO PIAUI","link":"http://www.portaltransparencia.gov.br/servidores/OrgaoExercicio-DetalhaServidor.asp?IdServidor=2087130&CodOrgao=26279"},{"name":"JOSE WELIGTON DE ANDRADE","job":"PROFESSOR DO MAGISTERIO SUPERIOR","link":"http://www.portaltransparencia.gov.br/servidores/OrgaoExercicio-DetalhaServidor.asp?IdServidor=1307620&CodOrgao=26279"},{"name":"JOSE WIRLEN BEZERRA DO NASCIMENTO","job":" - UNIVERSIDADE FEDERAL DO PIAUI","link":"http://www.portaltransparencia.gov.br/servidores/OrgaoExercicio-DetalhaServidor.asp?IdServidor=2084194&CodOrgao=26279"},{"name":"JOYCE RAMALHO SOUSA","job":" - UNIVERSIDADE FEDERAL DO PIAUI","link":"http://www.portaltransparencia.gov.br/servidores/OrgaoExercicio-DetalhaServidor.asp?IdServidor=2251896&CodOrgao=26279"},{"name":"JUAREZ DUARTE DE CARVALHO NETO","job":" - UNIVERSIDADE FEDERAL DO PIAUI","link":"http://www.portaltransparencia.gov.br/servidores/OrgaoExercicio-DetalhaServidor.asp?IdServidor=2149200&CodOrgao=26279"},{"name":"JULIANA ANGELINE TAPETY FERRO COSTA","job":" - UNIVERSIDADE FEDERAL DO PIAUI","link":"http://www.portaltransparencia.gov.br/servidores/OrgaoExercicio-DetalhaServidor.asp?IdServidor=2084633&CodOrgao=26279"},{"name":"JULIANA PARAGUASSU DEMES","job":" - UNIVERSIDADE FEDERAL DO PIAUI","link":"http://www.portaltransparencia.gov.br/servidores/OrgaoExercicio-DetalhaServidor.asp?IdServidor=2079695&CodOrgao=26279"},{"name":"JULIANA SOARES DO NASCIMENTO","job":"MEDICO - 24H","link":"http://www.portaltransparencia.gov.br/servidores/OrgaoExercicio-DetalhaServidor.asp?IdServidor=2033834&CodOrgao=26279"},{"name":"JULIANE NUNES PEREIRA COSTA","job":" - UNIVERSIDADE FEDERAL DO PIAUI","link":"http://www.portaltransparencia.gov.br/servidores/OrgaoExercicio-DetalhaServidor.asp?IdServidor=2084700&CodOrgao=26279"},{"name":"KAIULANY NASCIMENTO SOUSA","job":" - UNIVERSIDADE FEDERAL DO PIAUI","link":"http://www.portaltransparencia.gov.br/servidores/OrgaoExercicio-DetalhaServidor.asp?IdServidor=2086865&CodOrgao=26279"},{"name":"KAREN MARIA RODRIGUES DA COSTA","job":" - UNIVERSIDADE FEDERAL DO PIAUI","link":"http://www.portaltransparencia.gov.br/servidores/OrgaoExercicio-DetalhaServidor.asp?IdServidor=2079821&CodOrgao=26279"},{"name":"KARINA MOUSTAFA","job":" - UNIVERSIDADE FEDERAL DO PIAUI","link":"http://www.portaltransparencia.gov.br/servidores/OrgaoExercicio-DetalhaServidor.asp?IdServidor=2083341&CodOrgao=26279"},{"name":"KARLA CRISTINA MALTA VILANOVA","job":"PROFESSOR DO MAGISTERIO SUPERIOR","link":"http://www.portaltransparencia.gov.br/servidores/OrgaoExercicio-DetalhaServidor.asp?IdServidor=2002120&CodOrgao=26279"},{"name":"KARLA THAIS SOARES ALVES","job":" - UNIVERSIDADE FEDERAL DO PIAUI","link":"http://www.portaltransparencia.gov.br/servidores/OrgaoExercicio-DetalhaServidor.asp?IdServidor=2081231&CodOrgao=26279"},{"name":"KARLENE MARIA DA ROCHA FREITAS","job":" - UNIVERSIDADE FEDERAL DO PIAUI","link":"http://www.portaltransparencia.gov.br/servidores/OrgaoExercicio-DetalhaServidor.asp?IdServidor=2262710&CodOrgao=26279"},{"name":"KAROLINE FIGUEREDO RODRIGUES","job":" - UNIVERSIDADE FEDERAL DO PIAUI","link":"http://www.portaltransparencia.gov.br/servidores/OrgaoExercicio-DetalhaServidor.asp?IdServidor=2091358&CodOrgao=26279"},{"name":"KELLEN MATUZZY SILVA DE MELO","job":" - UNIVERSIDADE FEDERAL DO PIAUI","link":"http://www.portaltransparencia.gov.br/servidores/OrgaoExercicio-DetalhaServidor.asp?IdServidor=2086213&CodOrgao=26279"},{"name":"LAFAYETH FONTENELE BANDEIRA DE MACEDO","job":" - UNIVERSIDADE FEDERAL DO PIAUI","link":"http://www.portaltransparencia.gov.br/servidores/OrgaoExercicio-DetalhaServidor.asp?IdServidor=2256184&CodOrgao=26279"},{"name":"LAIO SANTANA PASSOS","job":" - UNIVERSIDADE FEDERAL DO PIAUI","link":"http://www.portaltransparencia.gov.br/servidores/OrgaoExercicio-DetalhaServidor.asp?IdServidor=2252744&CodOrgao=26279"},{"name":"LAIS PORTELA NEIVA COELHO","job":" - UNIVERSIDADE FEDERAL DO PIAUI","link":"http://www.portaltransparencia.gov.br/servidores/OrgaoExercicio-DetalhaServidor.asp?IdServidor=2249507&CodOrgao=26279"},{"name":"LAIZA CAVALCANTE DE CARVALHO CUNHA","job":" - UNIVERSIDADE FEDERAL DO PIAUI","link":"http://www.portaltransparencia.gov.br/servidores/OrgaoExercicio-DetalhaServidor.asp?IdServidor=2249441&CodOrgao=26279"},{"name":"LANA ANDRADE NAPOLEAO LIMA","job":" - UNIVERSIDADE FEDERAL DO PIAUI","link":"http://www.portaltransparencia.gov.br/servidores/OrgaoExercicio-DetalhaServidor.asp?IdServidor=2256662&CodOrgao=26279"},{"name":"LEONARDO ANTONIO DE CARVALHO HIPOLITO","job":" - UNIVERSIDADE FEDERAL DO PIAUI","link":"http://www.portaltransparencia.gov.br/servidores/OrgaoExercicio-DetalhaServidor.asp?IdServidor=2079000&CodOrgao=26279"},{"name":"LEONARDO LIMA CAMPELO","job":" - UNIVERSIDADE FEDERAL DO PIAUI","link":"http://www.portaltransparencia.gov.br/servidores/OrgaoExercicio-DetalhaServidor.asp?IdServidor=2105500&CodOrgao=26279"},{"name":"LEONARDO LINO MARTINS JUNIOR","job":" - UNIVERSIDADE FEDERAL DO PIAUI","link":"http://www.portaltransparencia.gov.br/servidores/OrgaoExercicio-DetalhaServidor.asp?IdServidor=2254919&CodOrgao=26279"},{"name":"LEONARDO RESENDE SANTANA","job":" - UNIVERSIDADE FEDERAL DO PIAUI","link":"http://www.portaltransparencia.gov.br/servidores/OrgaoExercicio-DetalhaServidor.asp?IdServidor=2235980&CodOrgao=26279"},{"name":"LIA JACYARA CHAVES PEREIRA","job":" - UNIVERSIDADE FEDERAL DO PIAUI","link":"http://www.portaltransparencia.gov.br/servidores/OrgaoExercicio-DetalhaServidor.asp?IdServidor=2088592&CodOrgao=26279"},{"name":"LILIAN LEITAO MONTEIRO","job":" - UNIVERSIDADE FEDERAL DO PIAUI","link":"http://www.portaltransparencia.gov.br/servidores/OrgaoExercicio-DetalhaServidor.asp?IdServidor=1679622&CodOrgao=26279"},{"name":"LIRIANY MARTINS PORTELA","job":" - UNIVERSIDADE FEDERAL DO PIAUI","link":"http://www.portaltransparencia.gov.br/servidores/OrgaoExercicio-DetalhaServidor.asp?IdServidor=1232696&CodOrgao=26279"},{"name":"LIVIA PARANAGUA DA PAZ MELO","job":" - UNIVERSIDADE FEDERAL DO PIAUI","link":"http://www.portaltransparencia.gov.br/servidores/OrgaoExercicio-DetalhaServidor.asp?IdServidor=2247645&CodOrgao=26279"},{"name":"LORENA LIMA BEZERRA","job":" - UNIVERSIDADE FEDERAL DO PIAUI","link":"http://www.portaltransparencia.gov.br/servidores/OrgaoExercicio-DetalhaServidor.asp?IdServidor=2249885&CodOrgao=26279"},{"name":"LORENA NORBERTA MENDES MOURA","job":" - UNIVERSIDADE FEDERAL DO PIAUI","link":"http://www.portaltransparencia.gov.br/servidores/OrgaoExercicio-DetalhaServidor.asp?IdServidor=2085480&CodOrgao=26279"},{"name":"LOURRANA DE MARIA LUZ ALVES CRONEMBERGER","job":" - UNIVERSIDADE FEDERAL DO PIAUI","link":"http://www.portaltransparencia.gov.br/servidores/OrgaoExercicio-DetalhaServidor.asp?IdServidor=1728358&CodOrgao=26279"},{"name":"LUAN BARROS DE SOUSA","job":" - UNIVERSIDADE FEDERAL DO PIAUI","link":"http://www.portaltransparencia.gov.br/servidores/OrgaoExercicio-DetalhaServidor.asp?IdServidor=2255784&CodOrgao=26279"},{"name":"LUARA PINHO FARIAS","job":" - UNIVERSIDADE FEDERAL DO PIAUI","link":"http://www.portaltransparencia.gov.br/servidores/OrgaoExercicio-DetalhaServidor.asp?IdServidor=2251301&CodOrgao=26279"},{"name":"LUCAS DE OLIVEIRA PINTO DE MESQUITA","job":" - UNIVERSIDADE FEDERAL DO PIAUI","link":"http://www.portaltransparencia.gov.br/servidores/OrgaoExercicio-DetalhaServidor.asp?IdServidor=1432150&CodOrgao=26279"},{"name":"LUCIANA FERREIRA DE SOUSA LUZ","job":" - UNIVERSIDADE FEDERAL DO PIAUI","link":"http://www.portaltransparencia.gov.br/servidores/OrgaoExercicio-DetalhaServidor.asp?IdServidor=2248405&CodOrgao=26279"},{"name":"LUIZ HENRIQUE CARVALHO DOS SANTOS","job":" - UNIVERSIDADE FEDERAL DO PIAUI","link":"http://www.portaltransparencia.gov.br/servidores/OrgaoExercicio-DetalhaServidor.asp?IdServidor=2248827&CodOrgao=26279"},{"name":"LUIZA ENIA DA SILVA ARAUJO","job":" - UNIVERSIDADE FEDERAL DO PIAUI","link":"http://www.portaltransparencia.gov.br/servidores/OrgaoExercicio-DetalhaServidor.asp?IdServidor=2091861&CodOrgao=26279"},{"name":"LUMA RAVENA SOARES MONTE","job":" - UNIVERSIDADE FEDERAL DO PIAUI","link":"http://www.portaltransparencia.gov.br/servidores/OrgaoExercicio-DetalhaServidor.asp?IdServidor=2091982&CodOrgao=26279"},{"name":"MAGNO RODRIGUES DE CARVALHO","job":" - UNIVERSIDADE FEDERAL DO PIAUI","link":"http://www.portaltransparencia.gov.br/servidores/OrgaoExercicio-DetalhaServidor.asp?IdServidor=2334734&CodOrgao=26279"},{"name":"MAISA GUIMARAES SILVA PRIMO","job":" - UNIVERSIDADE FEDERAL DO PIAUI","link":"http://www.portaltransparencia.gov.br/servidores/OrgaoExercicio-DetalhaServidor.asp?IdServidor=2247651&CodOrgao=26279"},{"name":"MAISA RAVENNA BELEZA LINO","job":" - UNIVERSIDADE FEDERAL DO PIAUI","link":"http://www.portaltransparencia.gov.br/servidores/OrgaoExercicio-DetalhaServidor.asp?IdServidor=2091912&CodOrgao=26279"},{"name":"MARCELA AGUIAR REIS","job":"PROFESSOR MAGISTERIO SUPERIOR-SUBSTITUTO","link":"http://www.portaltransparencia.gov.br/servidores/OrgaoExercicio-DetalhaServidor.asp?IdServidor=2155445&CodOrgao=26279"},{"name":"MARCELO JEAN VIEIRA LIMA","job":" - UNIVERSIDADE FEDERAL DO PIAUI","link":"http://www.portaltransparencia.gov.br/servidores/OrgaoExercicio-DetalhaServidor.asp?IdServidor=2261118&CodOrgao=26279"},{"name":"MARCELO VICTOR FREITAS NASCIMENTO","job":" - UNIVERSIDADE FEDERAL DO PIAUI","link":"http://www.portaltransparencia.gov.br/servidores/OrgaoExercicio-DetalhaServidor.asp?IdServidor=2266139&CodOrgao=26279"},{"name":"MARCIANO DA ROCHA RODRIGUES","job":" - UNIVERSIDADE FEDERAL DO PIAUI","link":"http://www.portaltransparencia.gov.br/servidores/OrgaoExercicio-DetalhaServidor.asp?IdServidor=2265422&CodOrgao=26279"},{"name":"MARCONNY BATISTA LIMA","job":" - UNIVERSIDADE FEDERAL DO PIAUI","link":"http://www.portaltransparencia.gov.br/servidores/OrgaoExercicio-DetalhaServidor.asp?IdServidor=2253693&CodOrgao=26279"},{"name":"MARCOS RENATO DE OLIVEIRA","job":"PROFESSOR DO MAGISTERIO SUPERIOR","link":"http://www.portaltransparencia.gov.br/servidores/OrgaoExercicio-DetalhaServidor.asp?IdServidor=1693580&CodOrgao=26279"},{"name":"MARCUS VINICIUS DE SOUZA PORTELA LEAL","job":" - UNIVERSIDADE FEDERAL DO PIAUI","link":"http://www.portaltransparencia.gov.br/servidores/OrgaoExercicio-DetalhaServidor.asp?IdServidor=1664923&CodOrgao=26279"},{"name":"MARIA BEATRIZ DOS SANTOS DIAS","job":" - UNIVERSIDADE FEDERAL DO PIAUI","link":"http://www.portaltransparencia.gov.br/servidores/OrgaoExercicio-DetalhaServidor.asp?IdServidor=2103028&CodOrgao=26279"},{"name":"MARIA CLARA FORTES PORTELA BOMFIM","job":" - UNIVERSIDADE FEDERAL DO PIAUI","link":"http://www.portaltransparencia.gov.br/servidores/OrgaoExercicio-DetalhaServidor.asp?IdServidor=2082781&CodOrgao=26279"},{"name":"MARIA CLARA LIMA ALMEIDA","job":" - UNIVERSIDADE FEDERAL DO PIAUI","link":"http://www.portaltransparencia.gov.br/servidores/OrgaoExercicio-DetalhaServidor.asp?IdServidor=1260387&CodOrgao=26279"},{"name":"MARIA DA GLORIA MARQUES AREA LEAO COSTA","job":"PEDAGOGO-AREA","link":"http://www.portaltransparencia.gov.br/servidores/OrgaoExercicio-DetalhaServidor.asp?IdServidor=1323429&CodOrgao=26279"},{"name":"MARIA DARISA DE SOUSA POLICARPO","job":" - UNIVERSIDADE FEDERAL DO PIAUI","link":"http://www.portaltransparencia.gov.br/servidores/OrgaoExercicio-DetalhaServidor.asp?IdServidor=2259424&CodOrgao=26279"},{"name":"MARIA DOLORES PINHEIRO RUFINO RIBEIRO","job":" - UNIVERSIDADE FEDERAL DO PIAUI","link":"http://www.portaltransparencia.gov.br/servidores/OrgaoExercicio-DetalhaServidor.asp?IdServidor=1499015&CodOrgao=26279"},{"name":"MARIANNE LIRA DE OLIVEIRA","job":" - UNIVERSIDADE FEDERAL DO PIAUI","link":"http://www.portaltransparencia.gov.br/servidores/OrgaoExercicio-DetalhaServidor.asp?IdServidor=2089029&CodOrgao=26279"},{"name":"MARILIA DE SOUSA SANTOS","job":" - UNIVERSIDADE FEDERAL DO PIAUI","link":"http://www.portaltransparencia.gov.br/servidores/OrgaoExercicio-DetalhaServidor.asp?IdServidor=2086074&CodOrgao=26279"},{"name":"MARINA PINTO SANCHES","job":" - UNIVERSIDADE FEDERAL DO PIAUI","link":"http://www.portaltransparencia.gov.br/servidores/OrgaoExercicio-DetalhaServidor.asp?IdServidor=2249343&CodOrgao=26279"},{"name":"MARINNA NERICA DO NASCIMENTO E SILVA","job":" - UNIVERSIDADE FEDERAL DO PIAUI","link":"http://www.portaltransparencia.gov.br/servidores/OrgaoExercicio-DetalhaServidor.asp?IdServidor=2081565&CodOrgao=26279"},{"name":"MARLLOS HENRIQUE VIEIRA NUNES","job":" - UNIVERSIDADE FEDERAL DO PIAUI","link":"http://www.portaltransparencia.gov.br/servidores/OrgaoExercicio-DetalhaServidor.asp?IdServidor=2085407&CodOrgao=26279"},{"name":"MATHEUS GREGORIO OLIVEIRA","job":" - UNIVERSIDADE FEDERAL DO PIAUI","link":"http://www.portaltransparencia.gov.br/servidores/OrgaoExercicio-DetalhaServidor.asp?IdServidor=2086002&CodOrgao=26279"},{"name":"MAYKON CALAND CAVALCANTE","job":" - UNIVERSIDADE FEDERAL DO PIAUI","link":"http://www.portaltransparencia.gov.br/servidores/OrgaoExercicio-DetalhaServidor.asp?IdServidor=2142259&CodOrgao=26279"},{"name":"MAYKON MARTINS DOS SANTOS","job":" - UNIVERSIDADE FEDERAL DO PIAUI","link":"http://www.portaltransparencia.gov.br/servidores/OrgaoExercicio-DetalhaServidor.asp?IdServidor=2251391&CodOrgao=26279"},{"name":"MICHELLE CHINTIA RODRIGUES DE SOUSA","job":"PROFESSOR MAGISTERIO SUPERIOR-SUBSTITUTO","link":"http://www.portaltransparencia.gov.br/servidores/OrgaoExercicio-DetalhaServidor.asp?IdServidor=2166423&CodOrgao=26279"},{"name":"MISAEL DAS VIRGENS SANTANA","job":" - UNIVERSIDADE FEDERAL DO PIAUI","link":"http://www.portaltransparencia.gov.br/servidores/OrgaoExercicio-DetalhaServidor.asp?IdServidor=2260197&CodOrgao=26279"},{"name":"MOACI FERREIRA DE MORAIS JUNIOR","job":" - UNIVERSIDADE FEDERAL DO PIAUI","link":"http://www.portaltransparencia.gov.br/servidores/OrgaoExercicio-DetalhaServidor.asp?IdServidor=1758169&CodOrgao=26279"},{"name":"MONALISA CAVALCANTE DE CARVALHO","job":" - UNIVERSIDADE FEDERAL DO PIAUI","link":"http://www.portaltransparencia.gov.br/servidores/OrgaoExercicio-DetalhaServidor.asp?IdServidor=1736762&CodOrgao=26279"},{"name":"NADYNE LORRAYNE FARIAS CARDOSO ROCHA","job":" - UNIVERSIDADE FEDERAL DO PIAUI","link":"http://www.portaltransparencia.gov.br/servidores/OrgaoExercicio-DetalhaServidor.asp?IdServidor=2247527&CodOrgao=26279"},{"name":"NALMA ALEXANDRA ROCHA DE CARVALHO","job":" - UNIVERSIDADE FEDERAL DO PIAUI","link":"http://www.portaltransparencia.gov.br/servidores/OrgaoExercicio-DetalhaServidor.asp?IdServidor=2085764&CodOrgao=26279"},{"name":"NARA MARIA RIBEIRO SOARES FERREIRA GOMES","job":" - UNIVERSIDADE FEDERAL DO PIAUI","link":"http://www.portaltransparencia.gov.br/servidores/OrgaoExercicio-DetalhaServidor.asp?IdServidor=1614800&CodOrgao=26279"},{"name":"NAYLA RAABE VENCAO DE MOURA","job":" - UNIVERSIDADE FEDERAL DO PIAUI","link":"http://www.portaltransparencia.gov.br/servidores/OrgaoExercicio-DetalhaServidor.asp?IdServidor=2143844&CodOrgao=26279"},{"name":"NAYRO DE SOUSA FERREIRA","job":" - UNIVERSIDADE FEDERAL DO PIAUI","link":"http://www.portaltransparencia.gov.br/servidores/OrgaoExercicio-DetalhaServidor.asp?IdServidor=2088544&CodOrgao=26279"},{"name":"ONIAS DE SOUSA RODRIGUES FILHO","job":" - UNIVERSIDADE FEDERAL DO PIAUI","link":"http://www.portaltransparencia.gov.br/servidores/OrgaoExercicio-DetalhaServidor.asp?IdServidor=2258780&CodOrgao=26279"},{"name":"PABLO LUIZ BEZERRA DE CASTRO","job":" - UNIVERSIDADE FEDERAL DO PIAUI","link":"http://www.portaltransparencia.gov.br/servidores/OrgaoExercicio-DetalhaServidor.asp?IdServidor=2256907&CodOrgao=26279"},{"name":"PABLO MARTINS VELOSO DE SOUSA","job":" - UNIVERSIDADE FEDERAL DO PIAUI","link":"http://www.portaltransparencia.gov.br/servidores/OrgaoExercicio-DetalhaServidor.asp?IdServidor=2258857&CodOrgao=26279"},{"name":"PAULA CAROLINE OLIVEIRA HENRIQUE SANTANA","job":" - UNIVERSIDADE FEDERAL DO PIAUI","link":"http://www.portaltransparencia.gov.br/servidores/OrgaoExercicio-DetalhaServidor.asp?IdServidor=2249723&CodOrgao=26279"},{"name":"PAULA LIMA DA SILVA","job":" - UNIVERSIDADE FEDERAL DO PIAUI","link":"http://www.portaltransparencia.gov.br/servidores/OrgaoExercicio-DetalhaServidor.asp?IdServidor=2082038&CodOrgao=26279"},{"name":"PAULO EDUARDO MUNIZ DE ANDRADE","job":" - UNIVERSIDADE FEDERAL DO PIAUI","link":"http://www.portaltransparencia.gov.br/servidores/OrgaoExercicio-DetalhaServidor.asp?IdServidor=2258010&CodOrgao=26279"},{"name":"PAULO HENRIQUE DE MELO FILHO","job":" - UNIVERSIDADE FEDERAL DO PIAUI","link":"http://www.portaltransparencia.gov.br/servidores/OrgaoExercicio-DetalhaServidor.asp?IdServidor=2257829&CodOrgao=26279"},{"name":"PAULO MONTEIRO ARAUJO","job":" - UNIVERSIDADE FEDERAL DO PIAUI","link":"http://www.portaltransparencia.gov.br/servidores/OrgaoExercicio-DetalhaServidor.asp?IdServidor=2250964&CodOrgao=26279"},{"name":"PAULO MOURA DE ARAUJO","job":" - UNIVERSIDADE FEDERAL DO PIAUI","link":"http://www.portaltransparencia.gov.br/servidores/OrgaoExercicio-DetalhaServidor.asp?IdServidor=2081157&CodOrgao=26279"},{"name":"PEDRO OLIVEIRA DOS SANTOS JUNIOR","job":" - UNIVERSIDADE FEDERAL DO PIAUI","link":"http://www.portaltransparencia.gov.br/servidores/OrgaoExercicio-DetalhaServidor.asp?IdServidor=2080375&CodOrgao=26279"},{"name":"PEDRO SAMUEL LIMA PEREIRA","job":" - UNIVERSIDADE FEDERAL DO PIAUI","link":"http://www.portaltransparencia.gov.br/servidores/OrgaoExercicio-DetalhaServidor.asp?IdServidor=2090811&CodOrgao=26279"},{"name":"POLYANA COUTINHO BENTO PEREIRA","job":" - UNIVERSIDADE FEDERAL DO PIAUI","link":"http://www.portaltransparencia.gov.br/servidores/OrgaoExercicio-DetalhaServidor.asp?IdServidor=2083600&CodOrgao=26279"},{"name":"PRISCILA DA SILVEIRA SANTOS","job":" - UNIVERSIDADE FEDERAL DO PIAUI","link":"http://www.portaltransparencia.gov.br/servidores/OrgaoExercicio-DetalhaServidor.asp?IdServidor=2088680&CodOrgao=26279"},{"name":"RAFAEL NUNES DE OLIVEIRA","job":" - UNIVERSIDADE FEDERAL DO PIAUI","link":"http://www.portaltransparencia.gov.br/servidores/OrgaoExercicio-DetalhaServidor.asp?IdServidor=1929638&CodOrgao=26279"},{"name":"RAFAELA CAVALCANTE BENIGNO","job":" - UNIVERSIDADE FEDERAL DO PIAUI","link":"http://www.portaltransparencia.gov.br/servidores/OrgaoExercicio-DetalhaServidor.asp?IdServidor=1224739&CodOrgao=26279"},{"name":"RAFAELLA CRISTHINE PORDEUS LUNA","job":"PROFESSOR DO MAGISTERIO SUPERIOR","link":"http://www.portaltransparencia.gov.br/servidores/OrgaoExercicio-DetalhaServidor.asp?IdServidor=1917323&CodOrgao=26279"},{"name":"RAIANA SOARES DE SOUSA SILVA","job":" - UNIVERSIDADE FEDERAL DO PIAUI","link":"http://www.portaltransparencia.gov.br/servidores/OrgaoExercicio-DetalhaServidor.asp?IdServidor=2080367&CodOrgao=26279"},{"name":"RAIMUNDO MOREIRA DOS SANTOS NETO","job":" - UNIVERSIDADE FEDERAL DO PIAUI","link":"http://www.portaltransparencia.gov.br/servidores/OrgaoExercicio-DetalhaServidor.asp?IdServidor=1856247&CodOrgao=26279"},{"name":"RAISA MELO VIEIRA","job":" - UNIVERSIDADE FEDERAL DO PIAUI","link":"http://www.portaltransparencia.gov.br/servidores/OrgaoExercicio-DetalhaServidor.asp?IdServidor=2251298&CodOrgao=26279"},{"name":"RAMIRO DE ARAUJO SOARES","job":" - UNIVERSIDADE FEDERAL DO PIAUI","link":"http://www.portaltransparencia.gov.br/servidores/OrgaoExercicio-DetalhaServidor.asp?IdServidor=2080650&CodOrgao=26279"},{"name":"RAPHAEL BERNARDO DA SILVA NETO","job":" - UNIVERSIDADE FEDERAL DO PIAUI","link":"http://www.portaltransparencia.gov.br/servidores/OrgaoExercicio-DetalhaServidor.asp?IdServidor=2254546&CodOrgao=26279"},{"name":"RAQUEL ALBUQUERQUE SILVA","job":" - UNIVERSIDADE FEDERAL DO PIAUI","link":"http://www.portaltransparencia.gov.br/servidores/OrgaoExercicio-DetalhaServidor.asp?IdServidor=2084457&CodOrgao=26279"},{"name":"RAY VICTOR GUIMARAES SERRA","job":"PROFESSOR MAGISTERIO SUPERIOR-SUBSTITUTO","link":"http://www.portaltransparencia.gov.br/servidores/OrgaoExercicio-DetalhaServidor.asp?IdServidor=2216486&CodOrgao=26279"},{"name":"REBECA BARBOSA DA ROCHA","job":" - UNIVERSIDADE FEDERAL DO PIAUI","link":"http://www.portaltransparencia.gov.br/servidores/OrgaoExercicio-DetalhaServidor.asp?IdServidor=2088990&CodOrgao=26279"},{"name":"REBEKA VALENCA NEVES","job":" - UNIVERSIDADE FEDERAL DO PIAUI","link":"http://www.portaltransparencia.gov.br/servidores/OrgaoExercicio-DetalhaServidor.asp?IdServidor=1525735&CodOrgao=26279"},{"name":"REGINA BEZERRA","job":" - UNIVERSIDADE FEDERAL DO PIAUI","link":"http://www.portaltransparencia.gov.br/servidores/OrgaoExercicio-DetalhaServidor.asp?IdServidor=2249890&CodOrgao=26279"},{"name":"REGINA PEREIRA LIMA REGO","job":"PROFESSOR 3 GRAU - SUBSTITUTO","link":"http://www.portaltransparencia.gov.br/servidores/OrgaoExercicio-DetalhaServidor.asp?IdServidor=1233643&CodOrgao=26279"},{"name":"REJANE EMILIA BARROS MENDES","job":" - UNIVERSIDADE FEDERAL DO PIAUI","link":"http://www.portaltransparencia.gov.br/servidores/OrgaoExercicio-DetalhaServidor.asp?IdServidor=2088645&CodOrgao=26279"},{"name":"RENAN BASTOS LEITE","job":" - UNIVERSIDADE FEDERAL DO PIAUI","link":"http://www.portaltransparencia.gov.br/servidores/OrgaoExercicio-DetalhaServidor.asp?IdServidor=2086920&CodOrgao=26279"},{"name":"RENATA MENDES DA SILVA","job":" - UNIVERSIDADE FEDERAL DO PIAUI","link":"http://www.portaltransparencia.gov.br/servidores/OrgaoExercicio-DetalhaServidor.asp?IdServidor=1442036&CodOrgao=26279"},{"name":"RICARDO COELHO FONTES","job":" - UNIVERSIDADE FEDERAL DO PIAUI","link":"http://www.portaltransparencia.gov.br/servidores/OrgaoExercicio-DetalhaServidor.asp?IdServidor=2091813&CodOrgao=26279"},{"name":"RICARDO DE OLIVEIRA CARVALHO","job":" - UNIVERSIDADE FEDERAL DO PIAUI","link":"http://www.portaltransparencia.gov.br/servidores/OrgaoExercicio-DetalhaServidor.asp?IdServidor=1659832&CodOrgao=26279"},{"name":"ROBERTA SOARES GONDIM MEDEIROS","job":" - UNIVERSIDADE FEDERAL DO PIAUI","link":"http://www.portaltransparencia.gov.br/servidores/OrgaoExercicio-DetalhaServidor.asp?IdServidor=2078704&CodOrgao=26279"},{"name":"ROBERTO NOLETO CAMPELO","job":" - UNIVERSIDADE FEDERAL DO PIAUI","link":"http://www.portaltransparencia.gov.br/servidores/OrgaoExercicio-DetalhaServidor.asp?IdServidor=2253273&CodOrgao=26279"},{"name":"ROSSANA FONSECA CASIMIRO","job":" - UNIVERSIDADE FEDERAL DO PIAUI","link":"http://www.portaltransparencia.gov.br/servidores/OrgaoExercicio-DetalhaServidor.asp?IdServidor=2256256&CodOrgao=26279"},{"name":"RYAN NOGUEIRA LIMA","job":" - UNIVERSIDADE FEDERAL DO PIAUI","link":"http://www.portaltransparencia.gov.br/servidores/OrgaoExercicio-DetalhaServidor.asp?IdServidor=2087311&CodOrgao=26279"},{"name":"SALATIEL MARTINS VIEIRA","job":" - UNIVERSIDADE FEDERAL DO PIAUI","link":"http://www.portaltransparencia.gov.br/servidores/OrgaoExercicio-DetalhaServidor.asp?IdServidor=1617125&CodOrgao=26279"},{"name":"SAMUEL ESTEVAN MOURA SANTOS GONCALVES","job":" - UNIVERSIDADE FEDERAL DO PIAUI","link":"http://www.portaltransparencia.gov.br/servidores/OrgaoExercicio-DetalhaServidor.asp?IdServidor=2255841&CodOrgao=26279"},{"name":"SAMUEL OLIVEIRA DA VERA","job":" - UNIVERSIDADE FEDERAL DO PIAUI","link":"http://www.portaltransparencia.gov.br/servidores/OrgaoExercicio-DetalhaServidor.asp?IdServidor=2081731&CodOrgao=26279"},{"name":"SAMYA RAQUEL SOARES DIAS","job":" - UNIVERSIDADE FEDERAL DO PIAUI","link":"http://www.portaltransparencia.gov.br/servidores/OrgaoExercicio-DetalhaServidor.asp?IdServidor=2118727&CodOrgao=26279"},{"name":"SARA BATISTA LIMA","job":" - UNIVERSIDADE FEDERAL DO PIAUI","link":"http://www.portaltransparencia.gov.br/servidores/OrgaoExercicio-DetalhaServidor.asp?IdServidor=2084812&CodOrgao=26279"},{"name":"SARITA SOUSA BASTOS","job":" - UNIVERSIDADE FEDERAL DO PIAUI","link":"http://www.portaltransparencia.gov.br/servidores/OrgaoExercicio-DetalhaServidor.asp?IdServidor=2091205&CodOrgao=26279"},{"name":"SAVIO FREIRE DA SILVA","job":" - UNIVERSIDADE FEDERAL DO PIAUI","link":"http://www.portaltransparencia.gov.br/servidores/OrgaoExercicio-DetalhaServidor.asp?IdServidor=2141134&CodOrgao=26279"},{"name":"SAVIO SOARES BARBOSA DANTAS","job":" - UNIVERSIDADE FEDERAL DO PIAUI","link":"http://www.portaltransparencia.gov.br/servidores/OrgaoExercicio-DetalhaServidor.asp?IdServidor=2080300&CodOrgao=26279"},{"name":"SERGIO DIEGO PASSOS COSTA","job":" - UNIVERSIDADE FEDERAL DO PIAUI","link":"http://www.portaltransparencia.gov.br/servidores/OrgaoExercicio-DetalhaServidor.asp?IdServidor=2084957&CodOrgao=26279"},{"name":"SILMARIA BANDEIRA DO NASCIMENTO","job":" - UNIVERSIDADE FEDERAL DO PIAUI","link":"http://www.portaltransparencia.gov.br/servidores/OrgaoExercicio-DetalhaServidor.asp?IdServidor=2266309&CodOrgao=26279"},{"name":"TAMARA TAYNNE TEIXEIRA DE OLIVEIRA","job":" - UNIVERSIDADE FEDERAL DO PIAUI","link":"http://www.portaltransparencia.gov.br/servidores/OrgaoExercicio-DetalhaServidor.asp?IdServidor=2258132&CodOrgao=26279"},{"name":"TATIANA RODRIGUES PRADO ALENCAR","job":" - UNIVERSIDADE FEDERAL DO PIAUI","link":"http://www.portaltransparencia.gov.br/servidores/OrgaoExercicio-DetalhaServidor.asp?IdServidor=2253738&CodOrgao=26279"},{"name":"TAYNAH EMANNUELLE COELHO DE FREITAS","job":" - UNIVERSIDADE FEDERAL DO PIAUI","link":"http://www.portaltransparencia.gov.br/servidores/OrgaoExercicio-DetalhaServidor.asp?IdServidor=2102491&CodOrgao=26279"},{"name":"THAINA PINTO DOS SANTOS","job":" - UNIVERSIDADE FEDERAL DO PIAUI","link":"http://www.portaltransparencia.gov.br/servidores/OrgaoExercicio-DetalhaServidor.asp?IdServidor=2084271&CodOrgao=26279"},{"name":"THALINE MILANY DA SILVA DIAS","job":" - UNIVERSIDADE FEDERAL DO PIAUI","link":"http://www.portaltransparencia.gov.br/servidores/OrgaoExercicio-DetalhaServidor.asp?IdServidor=2135379&CodOrgao=26279"},{"name":"THALITA MEDEIROS MELO","job":" - UNIVERSIDADE FEDERAL DO PIAUI","link":"http://www.portaltransparencia.gov.br/servidores/OrgaoExercicio-DetalhaServidor.asp?IdServidor=2079854&CodOrgao=26279"},{"name":"THAMARA BARROZO SAMPAIO","job":" - UNIVERSIDADE FEDERAL DO PIAUI","link":"http://www.portaltransparencia.gov.br/servidores/OrgaoExercicio-DetalhaServidor.asp?IdServidor=2251777&CodOrgao=26279"},{"name":"THAMIRIS DE SOUSA FEITOSA","job":" - UNIVERSIDADE FEDERAL DO PIAUI","link":"http://www.portaltransparencia.gov.br/servidores/OrgaoExercicio-DetalhaServidor.asp?IdServidor=2155856&CodOrgao=26279"},{"name":"THAMYRIS TABOSA DE SOUSA","job":" - UNIVERSIDADE FEDERAL DO PIAUI","link":"http://www.portaltransparencia.gov.br/servidores/OrgaoExercicio-DetalhaServidor.asp?IdServidor=2254493&CodOrgao=26279"},{"name":"THIAGO AUGUSTO TEIXEIRA CESAR","job":" - UNIVERSIDADE FEDERAL DO PIAUI","link":"http://www.portaltransparencia.gov.br/servidores/OrgaoExercicio-DetalhaServidor.asp?IdServidor=2089058&CodOrgao=26279"},{"name":"THIAGO DO NASCIMENTO RIBEIRO","job":" - UNIVERSIDADE FEDERAL DO PIAUI","link":"http://www.portaltransparencia.gov.br/servidores/OrgaoExercicio-DetalhaServidor.asp?IdServidor=1428624&CodOrgao=26279"},{"name":"THIAGO REGO ALBUQUERQUE","job":"ENFERMEIRO - 36H","link":"http://www.portaltransparencia.gov.br/servidores/OrgaoExercicio-DetalhaServidor.asp?IdServidor=2144814&CodOrgao=26279"},{"name":"THIAGO SOUSA DA SILVA","job":" - UNIVERSIDADE FEDERAL DO PIAUI","link":"http://www.portaltransparencia.gov.br/servidores/OrgaoExercicio-DetalhaServidor.asp?IdServidor=2253760&CodOrgao=26279"},{"name":"THULIO ADLEY LIMA CUNHA","job":" - UNIVERSIDADE FEDERAL DO PIAUI","link":"http://www.portaltransparencia.gov.br/servidores/OrgaoExercicio-DetalhaServidor.asp?IdServidor=2088482&CodOrgao=26279"},{"name":"TYSSIA DE SOUZA ALVES","job":" - UNIVERSIDADE FEDERAL DO PIAUI","link":"http://www.portaltransparencia.gov.br/servidores/OrgaoExercicio-DetalhaServidor.asp?IdServidor=1105538&CodOrgao=26279"},{"name":"VANESSA ANDRADE DE OLIVEIRA","job":" - UNIVERSIDADE FEDERAL DO PIAUI","link":"http://www.portaltransparencia.gov.br/servidores/OrgaoExercicio-DetalhaServidor.asp?IdServidor=2247641&CodOrgao=26279"},{"name":"VANESSA FEITOSA QUARESMA DE CARVALHO","job":" - UNIVERSIDADE FEDERAL DO PIAUI","link":"http://www.portaltransparencia.gov.br/servidores/OrgaoExercicio-DetalhaServidor.asp?IdServidor=1677497&CodOrgao=26279"},{"name":"VERIDIANA REBELO DOS SANTOS","job":" - UNIVERSIDADE FEDERAL DO PIAUI","link":"http://www.portaltransparencia.gov.br/servidores/OrgaoExercicio-DetalhaServidor.asp?IdServidor=2253772&CodOrgao=26279"},{"name":"VILKIANE NATERCIA MALHERME BARBOSA","job":" - UNIVERSIDADE FEDERAL DO PIAUI","link":"http://www.portaltransparencia.gov.br/servidores/OrgaoExercicio-DetalhaServidor.asp?IdServidor=2084422&CodOrgao=26279"},{"name":"VINICIUS DE ARAUJO COSTA COELHO","job":" - UNIVERSIDADE FEDERAL DO PIAUI","link":"http://www.portaltransparencia.gov.br/servidores/OrgaoExercicio-DetalhaServidor.asp?IdServidor=2164588&CodOrgao=26279"},{"name":"VINICIUS EULALIO BASILIO SOARES","job":" - UNIVERSIDADE FEDERAL DO PIAUI","link":"http://www.portaltransparencia.gov.br/servidores/OrgaoExercicio-DetalhaServidor.asp?IdServidor=2144195&CodOrgao=26279"},{"name":"VINY SAMPAIO DE BRITO","job":" - UNIVERSIDADE FEDERAL DO PIAUI","link":"http://www.portaltransparencia.gov.br/servidores/OrgaoExercicio-DetalhaServidor.asp?IdServidor=2250847&CodOrgao=26279"},{"name":"VITOR NUNES DE CASTRO LIMA","job":" - UNIVERSIDADE FEDERAL DO PIAUI","link":"http://www.portaltransparencia.gov.br/servidores/OrgaoExercicio-DetalhaServidor.asp?IdServidor=2078831&CodOrgao=26279"},{"name":"VIVIANE DOS SANTOS SILVA","job":" - UNIVERSIDADE FEDERAL DO PIAUI","link":"http://www.portaltransparencia.gov.br/servidores/OrgaoExercicio-DetalhaServidor.asp?IdServidor=2080764&CodOrgao=26279"},{"name":"VIVIANE PINHEIRO ALVES DE ALMEIDA","job":" - UNIVERSIDADE FEDERAL DO PIAUI","link":"http://www.portaltransparencia.gov.br/servidores/OrgaoExercicio-DetalhaServidor.asp?IdServidor=2082135&CodOrgao=26279"},{"name":"VIVIANNE SANTANA GALVAO PINHEIRO","job":" - UNIVERSIDADE FEDERAL DO PIAUI","link":"http://www.portaltransparencia.gov.br/servidores/OrgaoExercicio-DetalhaServidor.asp?IdServidor=2266675&CodOrgao=26279"},{"name":"VIVIANY DE SOUSA RODRIGUES","job":" - UNIVERSIDADE FEDERAL DO PIAUI","link":"http://www.portaltransparencia.gov.br/servidores/OrgaoExercicio-DetalhaServidor.asp?IdServidor=2090051&CodOrgao=26279"},{"name":"WELLAYNY CHRISTYAN RIBEIRO DE CARVALHO","job":" - UNIVERSIDADE FEDERAL DO PIAUI","link":"http://www.portaltransparencia.gov.br/servidores/OrgaoExercicio-DetalhaServidor.asp?IdServidor=2091338&CodOrgao=26279"},{"name":"WERNER ROCHA ALBUQUERQUE","job":" - UNIVERSIDADE FEDERAL DO PIAUI","link":"http://www.portaltransparencia.gov.br/servidores/OrgaoExercicio-DetalhaServidor.asp?IdServidor=2085876&CodOrgao=26279"},{"name":"YSLLA FERNANDA FITZ BALO MERIGUETI","job":" - UNIVERSIDADE FEDERAL DO PIAUI","link":"http://www.portaltransparencia.gov.br/servidores/OrgaoExercicio-DetalhaServidor.asp?IdServidor=2250994&CodOrgao=26279"}]